elb_log_parser
