Metadata-Version: 1.1
Name: elb-log-parser
Version: 0.0.2
Summary: AWS Elastic Load Balancing log parser.
Home-page: https://github.com/leandrosouza/elb-log-parser
Author: Leandro Souza
Author-email: lsouzarj@gmail.com
License: MIT
Keywords: AWS Elastic Load Balancing log parser python
Platform: UNKNOWN
Classifier: Development Status :: 4 - Beta
Classifier: Intended Audience :: Developers
Classifier: License :: OSI Approved :: MIT License
Classifier: Natural Language :: English
Classifier: Operating System :: Unix
Classifier: Programming Language :: Python :: 2.7
Classifier: Programming Language :: Python :: 3.4
Classifier: Programming Language :: Python :: Implementation :: PyPy
Classifier: Operating System :: OS Independent
